spype/__init__.py
spype/callbacks.py
spype/constants.py
spype/exceptions.py
spype/types.py
spype/utils.py
spype/version.py
spype/core/__init__.py
spype/core/digraph.py
spype/core/pype.py
spype/core/sbase.py
spype/core/task.py
spype/core/wrap.py
spype-0.0.0.dist-info/DESCRIPTION.rst
spype-0.0.0.dist-info/METADATA
spype-0.0.0.dist-info/RECORD
spype-0.0.0.dist-info/WHEEL
spype-0.0.0.dist-info/metadata.json
spype-0.0.0.dist-info/top_level.txt
