Metadata-Version: 2.0
Name: spype
Version: 0.0.0
Summary: A lightweight data pipeline
Home-page: https://github.com/d-chambers/spype
Author: Derrick Chambers
Author-email: djachambeador@gmail.com
License: BSD
Keywords: data pipeline
Platform: UNKNOWN
Classifier: Development Status :: 3 - Alpha
Classifier: Intended Audience :: Developers
Classifier: License :: OSI Approved :: BSD License
Classifier: Programming Language :: Python :: 3.6
Requires-Python: >=3.6
